{"otherData": {},"traceEvents":[{"cat":"function","dur":33753,"name":"glfwInit","ph":"X","pid":0,"tid":2313889995,"ts":893009958601},{"cat":"function","dur":272162,"name":"glfwCreatewindow","ph":"X","pid":0,"tid":2313889995,"ts":893009992508},{"cat":"function","dur":5139,"name":"void __cdecl Evadne::OpenGLContext::Init(void)","ph":"X","pid":0,"tid":2313889995,"ts":893010264805},{"cat":"function","dur":34,"name":"void __cdecl Evadne::WindowsWindow::SetVSync(bool)","ph":"X","pid":0,"tid":2313889995,"ts":893010270004},{"cat":"function","dur":312987,"name":"void __cdecl Evadne::WindowsWindow::Init(const struct Evadne::WindowProps &)","ph":"X","pid":0,"tid":2313889995,"ts":893009957080},{"cat":"function","dur":313010,"name":"__cdecl Evadne::WindowsWindow::WindowsWindow(const struct Evadne::WindowProps &)","ph":"X","pid":0,"tid":2313889995,"ts":893009957078},{"cat":"function","dur":7,"name":"void __cdecl Evadne::OpenGLRendererAPI::Init(void)","ph":"X","pid":0,"tid":2313889995,"ts":893010270131},{"cat":"function","dur":31,"name":"__cdecl Evadne::OpenGLVertexArray::OpenGLVertexArray(void)","ph":"X","pid":0,"tid":2313889995,"ts":893010270173},{"cat":"function","dur":26,"name":"__cdecl Evadne::OpenGLVertexBuffer::OpenGLVertexBuffer(float *,unsigned int)","ph":"X","pid":0,"tid":2313889995,"ts":893010270252},{"cat":"function","dur":0,"name":"void __cdecl Evadne::OpenGLVertexBuffer::Bind(void) const","ph":"X","pid":0,"tid":2313889995,"ts":893010270640},{"cat":"function","dur":346,"name":"void __cdecl Evadne::OpenGLVertexArray::AddVertexBuffer(const class std::shared_ptr<class Evadne::VertexBuffer> &)","ph":"X","pid":0,"tid":2313889995,"ts":893010270322},{"cat":"function","dur":36,"name":"__cdecl Evadne::OpenGLIndexBuffer::OpenGLIndexBuffer(unsigned int *,unsigned int)","ph":"X","pid":0,"tid":2313889995,"ts":893010270689},{"cat":"function","dur":0,"name":"void __cdecl Evadne::OpenGLIndexBuffer::Bind(void) const","ph":"X","pid":0,"tid":2313889995,"ts":893010270760},{"cat":"function","dur":22,"name":"void __cdecl Evadne::OpenGLVertexArray::SetIndexBuffer(const class std::shared_ptr<class Evadne::IndexBuffer> &)","ph":"X","pid":0,"tid":2313889995,"ts":893010270759},{"cat":"function","dur":37,"name":"__cdecl Evadne::OpenGLTexture2D::OpenGLTexture2D(unsigned int,unsigned int)","ph":"X","pid":0,"tid":2313889995,"ts":893010270805},{"cat":"function","dur":8,"name":"void __cdecl Evadne::OpenGLTexture2D::SetData(void *,unsigned int)","ph":"X","pid":0,"tid":2313889995,"ts":893010270865},{"cat":"function","dur":220,"name":"class std::basic_string<char,struct std::char_traits<char>,class std::allocator<char> > __cdecl Evadne::OpenGLShader::ReadFile(const class std::basic_string<char,struct std::char_traits<char>,class std::allocator<char> > &)","ph":"X","pid":0,"tid":2313889995,"ts":893010270899},{"cat":"function","dur":25,"name":"class std::unordered_map<unsigned int,class std::basic_string<char,struct std::char_traits<char>,class std::allocator<char> >,struct std::hash<unsigned int>,struct std::equal_to<unsigned int>,class std::allocator<struct std::pair<unsigned int const ,class std::basic_string<char,struct std::char_traits<char>,class std::allocator<char> > > > > __cdecl Evadne::OpenGLShader::PreProcess(const class std::basic_string<char,struct std::char_traits<char>,class std::allocator<char> > &)","ph":"X","pid":0,"tid":2313889995,"ts":893010271155},{"cat":"function","dur":663,"name":"void __cdecl Evadne::OpenGLShader::Compile(const class std::unordered_map<unsigned int,class std::basic_string<char,struct std::char_traits<char>,class std::allocator<char> >,struct std::hash<unsigned int>,struct std::equal_to<unsigned int>,class std::allocator<struct std::pair<unsigned int const ,class std::basic_string<char,struct std::char_traits<char>,class std::allocator<char> > > > > &)","ph":"X","pid":0,"tid":2313889995,"ts":893010271206},{"cat":"function","dur":1020,"name":"__cdecl Evadne::OpenGLShader::OpenGLShader(const class std::basic_string<char,struct std::char_traits<char>,class std::allocator<char> > &)","ph":"X","pid":0,"tid":2313889995,"ts":893010270898},{"cat":"function","dur":3,"name":"void __cdecl Evadne::OpenGLShader::Bind(void) const","ph":"X","pid":0,"tid":2313889995,"ts":893010271980},{"cat":"function","dur":38,"name":"void __cdecl Evadne::OpenGLShader::SetInt(const class std::basic_string<char,struct std::char_traits<char>,class std::allocator<char> > &,int)","ph":"X","pid":0,"tid":2313889995,"ts":893010272010},{"cat":"function","dur":1925,"name":"void __cdecl Evadne::Renderer2D::Init(void)","ph":"X","pid":0,"tid":2313889995,"ts":893010270163},{"cat":"function","dur":1987,"name":"void __cdecl Evadne::Renderer::Init(void)","ph":"X","pid":0,"tid":2313889995,"ts":893010270122},{"cat":"function","dur":1350,"name":"void __cdecl Evadne::ImGuiLayer::OnAttach(void)","ph":"X","pid":0,"tid":2313889995,"ts":893010272139},{"cat":"function","dur":1392,"name":"void __cdecl Evadne::Application::PushOverlay(class Evadne::Layer *)","ph":"X","pid":0,"tid":2313889995,"ts":893010272133},{"cat":"function","dur":316479,"name":"__cdecl Evadne::Application::Application(void)","ph":"X","pid":0,"tid":2313889995,"ts":893009957066},{"cat":"function","dur":4,"name":"__cdecl Evadne::OrthographicCamera::OrthographicCamera(float,float,float,float)","ph":"X","pid":0,"tid":2313889995,"ts":893010273572},{"cat":"function","dur":185965,"name":"stbi_load - OpenGLTexture2D::OpenGLTexture2D(const std:string&)","ph":"X","pid":0,"tid":2313889995,"ts":893010273603},{"cat":"function","dur":200160,"name":"__cdecl Evadne::OpenGLTexture2D::OpenGLTexture2D(const class std::basic_string<char,struct std::char_traits<char>,class std::allocator<char> > &)","ph":"X","pid":0,"tid":2313889995,"ts":893010273601},{"cat":"function","dur":200368,"name":"void __cdecl Sandbox2D::OnAttach(void)","ph":"X","pid":0,"tid":2313889995,"ts":893010273599},{"cat":"function","dur":200437,"name":"void __cdecl Evadne::Application::PushLayer(class Evadne::Layer *)","ph":"X","pid":0,"tid":2313889995,"ts":893010273596}]}